README.txt
setup.py
bin/mobiko
mobiko/__init__.py
mobiko/__main__.py
mobiko/cli.py
mobiko/conversion.py
mobiko/pbx.py
mobiko/template.py
mobiko.egg-info/PKG-INFO
mobiko.egg-info/SOURCES.txt
mobiko.egg-info/dependency_links.txt
mobiko.egg-info/requires.txt
mobiko.egg-info/top_level.txt