Metadata-Version: 1.0
Name: mobiko
Version: 0.3.0
Summary: Make images for iOS app icon from a big PNG
Home-page: https://github.com/gamikun/mobiko
Author: Gamaliel Espinoza M.
Author-email: gamaliel.espinoza@gmail.com
License: UNKNOWN
Keywords: image,icons,
Platform: UNKNOWN
